libremarkable/__init__.py
libremarkable/_battery.py
libremarkable/_color.py
libremarkable/_device.py
libremarkable/_framebuffer.py
libremarkable/_input.py
libremarkable/_ioctl.py
libremarkable/_keymap.py
libremarkable/_libc.py
libremarkable/_mxcfb.py
libremarkable/_rm2fb.py
libremarkable/geometry.py
libremarkable-0.0.1.dist-info/LICENSE
libremarkable-0.0.1.dist-info/METADATA
libremarkable-0.0.1.dist-info/WHEEL
libremarkable-0.0.1.dist-info/top_level.txt
libremarkable-0.0.1.dist-info/RECORD
